antispam/__init__.py
antispam/main.py
as_python/__init__.py
as_python/main.py
onetimeantispam-1.1.dist-info/METADATA
onetimeantispam-1.1.dist-info/WHEEL
onetimeantispam-1.1.dist-info/top_level.txt
onetimeantispam-1.1.dist-info/RECORD
