Metadata-Version: 2.1
Name: onetimeantispam
Version: 1.1
Summary: AntiSpam
Home-page: https://github.com/onetimegithub
Author: onetimedev
Author-email: onetimedev@mail.ru
Requires-Dist: aiohttp
